xorq_feature_utils/__init__.py
xorq_feature_utils-0.1.1.dist-info/METADATA
xorq_feature_utils-0.1.1.dist-info/WHEEL
xorq_feature_utils-0.1.1.dist-info/RECORD
