Metadata-Version: 2.4
Name: xorq-feature-utils
Version: 0.1.1
Summary: Add your description here
Requires-Python: >=3.10
Requires-Dist: attrs>=25.3.0
Requires-Dist: pandas>=2.3.0
Requires-Dist: pyarrow>=20.0.0
Requires-Dist: requests>=2.32.3
Requires-Dist: toolz>=1.0.0
Requires-Dist: urllib3>=2.2.3
Requires-Dist: xorq>=0.3.1
